marktask.py
marktask-0.0a4.dist-info/METADATA
marktask-0.0a4.dist-info/WHEEL
marktask-0.0a4.dist-info/top_level.txt
marktask-0.0a4.dist-info/RECORD
