Metadata-Version: 2.1
Name: marktask
Version: 0.0a4
Summary: Marking files and folder with task states and list them afterwards.
Home-page: https://gitlab.com/david.scheliga/marktask
Author: David Scheliga
Author-email: david.scheliga@gmx.de
License: GNU General Public License v3 (GPLv3)
Keywords: mark,file,folder
Platform: UNKNOWN
Classifier: Development Status :: 3 - Alpha
Classifier: License :: OSI Approved :: GNU General Public License v3 (GPLv3)
Classifier: Operating System :: OS Independent
Classifier: Programming Language :: Python :: 3
Requires-Python: >=3.6
